{
  "A": [
    {
      "q": "地球から最も近い天体は？",
      "l": "月",
      "r": "太陽",
      "a": "left"
    },
    {
      "q": "光合成で植物が放出するものは？",
      "l": "二酸化炭素",
      "r": "酸素",
      "a": "right"
    },
    {
      "q": "人体で最も長い骨は？",
      "l": "脛骨",
      "r": "大腿骨",
      "a": "right"
    },
    {
      "q": "音と光、空気中で速いのはどっち？",
      "l": "音",
      "r": "光",
      "a": "right"
    },
    {
      "q": "血液を全身に送る器官は？",
      "l": "心臓",
      "r": "肺",
      "a": "left"
    },
    {
      "q": "元素記号「Fe」は何？",
      "l": "鉄",
      "r": "銅",
      "a": "left"
    },
    {
      "q": "光合成が行われる細胞小器官は？",
      "l": "葉緑体",
      "r": "ミトコンドリア",
      "a": "left"
    },
    {
      "q": "人体で最も多い元素（重量比）は？",
      "l": "酸素",
      "r": "炭素",
      "a": "left"
    },
    {
      "q": "地球の内核を主に構成する物質は？",
      "l": "ケイ素",
      "r": "鉄・ニッケル",
      "a": "right"
    },
    {
      "q": "最終問題：DNAの二重らせん構造を発見したのは？",
      "l": "ワトソンとクリック",
      "r": "キュリーとピエール",
      "a": "left"
    }
  ],
  "B": [
    {
      "q": "日本の国旗は何色の組み合わせ？",
      "l": "赤と白",
      "r": "青と白",
      "a": "left"
    },
    {
      "q": "世界で最も小さい国は？",
      "l": "モナコ",
      "r": "バチカン",
      "a": "right"
    },
    {
      "q": "ナイル川が流れる大陸は？",
      "l": "アフリカ",
      "r": "アジア",
      "a": "left"
    },
    {
      "q": "日本で最も南にある都道府県は？",
      "l": "鹿児島",
      "r": "沖縄",
      "a": "right"
    },
    {
      "q": "第二次世界大戦が終わった年は？",
      "l": "1945年",
      "r": "1946年",
      "a": "left"
    },
    {
      "q": "日本の都道府県の数は？",
      "l": "47",
      "r": "46",
      "a": "left"
    },
    {
      "q": "江戸幕府を開いたのは？",
      "l": "徳川秀忠",
      "r": "徳川家康",
      "a": "right"
    },
    {
      "q": "世界遺産「マチュ・ピチュ」がある国は？",
      "l": "ブラジル",
      "r": "ペルー",
      "a": "right"
    },
    {
      "q": "日本が国連に加盟した年は？",
      "l": "1956年",
      "r": "1951年",
      "a": "left"
    },
    {
      "q": "最終問題：フランス革命が起きた年は？",
      "l": "1789年",
      "r": "1799年",
      "a": "left"
    }
  ],
  "C": [
    {
      "q": "モナ・リザを描いた人物は？",
      "l": "ダ・ヴィンチ",
      "r": "ミケランジェロ",
      "a": "left"
    },
    {
      "q": "「ドラえもん」のポケットの名前は？",
      "l": "四次元ポケット",
      "r": "宇宙ポケット",
      "a": "left"
    },
    {
      "q": "「赤ずきん」でおばあさんに化けた動物は？",
      "l": "オオカミ",
      "r": "キツネ",
      "a": "left"
    },
    {
      "q": "ベートーヴェンの「第九」は交響曲第何番？",
      "l": "第7番",
      "r": "第9番",
      "a": "right"
    },
    {
      "q": "「ゲルニカ」を描いた画家は？",
      "l": "マティス",
      "r": "ピカソ",
      "a": "right"
    },
    {
      "q": "「走れメロス」の作者は？",
      "l": "芥川龍之介",
      "r": "太宰治",
      "a": "right"
    },
    {
      "q": "芥川龍之介の「羅生門」の原作となった書物は？",
      "l": "今昔物語",
      "r": "源氏物語",
      "a": "left"
    },
    {
      "q": "「エルミタージュ美術館」がある国は？",
      "l": "ロシア",
      "r": "フランス",
      "a": "left"
    },
    {
      "q": "シェイクスピアの「四大悲劇」のひとつは？",
      "l": "ロミオとジュリエット",
      "r": "ハムレット",
      "a": "right"
    },
    {
      "q": "最終問題：バッハの「G線上のアリア」の原曲は管弦楽組曲第何番？",
      "l": "第3番",
      "r": "第4番",
      "a": "left"
    }
  ],
  "D": [
    {
      "q": "三角形の内角の和は？",
      "l": "180度",
      "r": "360度",
      "a": "left"
    },
    {
      "q": "10の2乗は？",
      "l": "10000",
      "r": "100",
      "a": "right"
    },
    {
      "q": "素数はどっち？",
      "l": "11",
      "r": "15",
      "a": "left"
    },
    {
      "q": "円の面積の公式は？",
      "l": "πr²",
      "r": "2πr",
      "a": "left"
    },
    {
      "q": "1から10までの整数の和は？",
      "l": "45",
      "r": "55",
      "a": "right"
    },
    {
      "q": "√2の近似値は？",
      "l": "約1.41",
      "r": "約1.73",
      "a": "left"
    },
    {
      "q": "2の10乗は？",
      "l": "1024",
      "r": "2048",
      "a": "left"
    },
    {
      "q": "正六角形の1つの内角は？",
      "l": "120度",
      "r": "135度",
      "a": "left"
    },
    {
      "q": "フィボナッチ数列（1,1,2,3,5,8…）の10番目は？",
      "l": "55",
      "r": "34",
      "a": "left"
    },
    {
      "q": "最終問題：1から100までの整数の和は？",
      "l": "4950",
      "r": "5050",
      "a": "right"
    }
  ]
}
